autordf2gml/__init__.py
autordf2gml/cb.py
autordf2gml/cbsimple.py
autordf2gml/tb.py
autordf2gml/utils.py
autordf2gml-0.0.1.dist-info/METADATA
autordf2gml-0.0.1.dist-info/WHEEL
autordf2gml-0.0.1.dist-info/top_level.txt
autordf2gml-0.0.1.dist-info/RECORD
