Metadata-Version: 2.1
Name: autordf2gml
Version: 0.0.1
Summary: AutoRDF2GML: A Framework for Transforming RDF Data into Graph Representations for Graph Machine Learning.
Author-email: Michael Faerber <michael.faerber@tu-dresden.de>, David Lamprecht <lamprecht.david@web.de>, Yuni Susanti <yuni.susanti@mailbox.tu-dresden.de>
License: MIT License
Project-URL: Homepage, https://github.com/davidlamprecht/AutoRDF2GML
Project-URL: Issues, https://github.com/davidlamprecht/AutoRDF2GML/issues
Keywords: rdf,graph dataset,knowledge graph,autordf2gml,gml,gnn
Classifier: Intended Audience :: Developers
Classifier: Topic :: Software Development :: Libraries :: Python Modules
Classifier: Programming Language :: Python :: 3.8
Classifier: License :: OSI Approved :: MIT License
Requires-Python: <=3.9.9,>=3.8
Requires-Dist: rdflib ~=6.3.2
Requires-Dist: pandas ~=1.3.5
Requires-Dist: numpy ~=1.22.4
Requires-Dist: configparser ~=6.0.0
Requires-Dist: scikit-learn ~=1.1.1
Requires-Dist: torch ~=1.12.0
Requires-Dist: transformers ~=4.30.2
Requires-Dist: tqdm ~=4.65.0
Requires-Dist: torch-geometric ~=2.3.0
Requires-Dist: urllib3 ~=1.26.6
